count_api/__init__.py
count_api/count_api.py
count_api/table.py
count_api/api_requests/__init__.py
count_api/api_requests/api_requests.py
count_api/column/__init__.py
count_api/column/column.py
count_api/table_tile/__init__.py
count_api/table_tile/row_indices.py
count_api/table_tile/table_tile.py
count_api/table_tile/column_tiles/__init__.py
count_api/table_tile/column_tiles/column_tile.py
count_api/table_tile/column_tiles/datetime_column_tile.py
count_api/table_tile/column_tiles/double_column_tile.py
count_api/table_tile/column_tiles/double_range_column_tile.py
count_api/table_tile/column_tiles/int_column_tile.py
count_api/table_tile/column_tiles/int_range_column_tile.py
count_api/table_tile/column_tiles/string_column_tile.py
count_api/table_tile/pbf/__init__.py
count_api/table_tile/pbf/table_tile_pb2.py
count_api/util/__init__.py
count_api/visual/__init__.py
count_api/visual/visual.py
count_api/visual_helper/__init__.py
count_api/visual_helper/visual_helper.py
count_api-3.1.9.dist-info/LICENSE
count_api-3.1.9.dist-info/METADATA
count_api-3.1.9.dist-info/WHEEL
count_api-3.1.9.dist-info/top_level.txt
count_api-3.1.9.dist-info/RECORD
