Metadata-Version: 2.1
Name: count-api
Version: 3.1.9
Summary: API client for count.co
Home-page: https://count.co
Author: Count Technologies LTD
Author-email: hello@count.co
License: UNKNOWN
Platform: UNKNOWN
Classifier: Programming Language :: Python
Classifier: License :: OSI Approved :: MIT License
Classifier: Operating System :: OS Independent
Requires-Dist: requests
Requires-Dist: protobuf (==3.5.1)
Requires-Dist: future
Requires-Dist: pyhamcrest
Requires-Dist: six
